{
	"configurations" : 
	[
		{
			"directories" : 
			[
				{
					"build" : ".",
					"jsonFile" : "directory-.-Debug-f5ebdc15457944623624.json",
					"minimumCMakeVersion" : 
					{
						"string" : "3.21"
					},
					"projectIndex" : 0,
					"source" : ".",
					"targetIndexes" : 
					[
						0
					]
				}
			],
			"name" : "Debug",
			"projects" : 
			[
				{
					"directoryIndexes" : 
					[
						0
					],
					"name" : "2021_12_24",
					"targetIndexes" : 
					[
						0
					]
				}
			],
			"targets" : 
			[
				{
					"directoryIndex" : 0,
					"id" : "2021_12_24::@6890427a1f51a3e7e1df",
					"jsonFile" : "target-2021_12_24-Debug-49707687bdbaae4e5793.json",
					"name" : "2021_12_24",
					"projectIndex" : 0
				}
			]
		}
	],
	"kind" : "codemodel",
	"paths" : 
	{
		"build" : "/Users/b_white/JetBrains/CLionProjects/2021.12.24/cmake-build-debug",
		"source" : "/Users/b_white/JetBrains/CLionProjects/2021.12.24"
	},
	"version" : 
	{
		"major" : 2,
		"minor" : 3
	}
}
